LICENSE
MANIFEST.in
README.md
setup.py
monkeytime/__init__.py
monkeytime/monkeydatetime.py
monkeytime.egg-info/PKG-INFO
monkeytime.egg-info/SOURCES.txt
monkeytime.egg-info/dependency_links.txt
monkeytime.egg-info/top_level.txt